swiftcrypt/__init__.py
swiftcrypt/swiftcrypt.py
swiftcrypt-0.3.5.11.dist-info/METADATA
swiftcrypt-0.3.5.11.dist-info/WHEEL
swiftcrypt-0.3.5.11.dist-info/top_level.txt
swiftcrypt-0.3.5.11.dist-info/RECORD
