Metadata-Version: 2.1
Name: swiftcrypt
Version: 0.3.5.11
Summary: Swiftly Secure your Apps
Author: Tech Tweaks
Author-email: tech.tweaks.contact@gmail.com
Keywords: keys,passwords,crypting,encoding,secure,uuid
Classifier: Development Status :: 5 - Production/Stable
Classifier: Intended Audience :: Developers
Classifier: License :: OSI Approved :: MIT License
Classifier: Programming Language :: Python :: 3.8
Classifier: Programming Language :: Python :: 3.9
Classifier: Programming Language :: Python :: 3.10
Classifier: Programming Language :: Python :: 3.11
Classifier: Operating System :: Microsoft :: Windows
Requires-Dist: bcrypt ==4.0.1
Requires-Dist: pyotp ==2.9.0
Requires-Dist: qrcode ==7.4.2
Requires-Dist: cryptography ==41.0.3
Requires-Dist: keyring ==24.2.0
